napari_activelearning/__init__.py
napari_activelearning/_acquisition.py
napari_activelearning/_interface.py
napari_activelearning/_labels.py
napari_activelearning/_layers.py
napari_activelearning/_models.py
napari_activelearning/_models_impl.py
napari_activelearning/_models_impl_interface.py
napari_activelearning/_utils.py
napari_activelearning/_version.py
napari_activelearning/_widgets.py
napari_activelearning/napari.yaml
napari_activelearning/_tests/__init__.py
napari_activelearning/_tests/conftest.py
napari_activelearning/_tests/test_acquisition.py
napari_activelearning/_tests/test_layers.py
napari_activelearning/_tests/test_utils.py
napari_activelearning-0.1.0.dist-info/licenses/LICENSE
napari_activelearning-0.1.0.dist-info/METADATA
napari_activelearning-0.1.0.dist-info/WHEEL
napari_activelearning-0.1.0.dist-info/entry_points.txt
napari_activelearning-0.1.0.dist-info/top_level.txt
napari_activelearning-0.1.0.dist-info/RECORD
