Metadata-Version: 2.4
Name: napari-activelearning
Version: 0.1.0
Summary: An active learning plugin for fine tuning of deep learning models.
Author: Fernando Cervantes (The Jackson Laboratory)
Author-email: fernando.cervantes@jax.org
License: MIT License
Project-URL: Homepage, https://github.com/TheJacksonLaboratory/activelearning
Classifier: Development Status :: 2 - Pre-Alpha
Classifier: Framework :: napari
Classifier: Intended Audience :: Developers
Classifier: License :: OSI Approved :: MIT License
Classifier: Operating System :: OS Independent
Classifier: Programming Language :: Python
Classifier: Programming Language :: Python :: 3
Classifier: Programming Language :: Python :: 3 :: Only
Classifier: Programming Language :: Python :: 3.10
Classifier: Programming Language :: Python :: 3.11
Classifier: Programming Language :: Python :: 3.12
Classifier: Topic :: Scientific/Engineering :: Image Processing
Requires-Python: >=3.10
License-File: LICENSE
Requires-Dist: napari
Requires-Dist: numpy
Requires-Dist: dask[array]
Requires-Dist: magicgui
Requires-Dist: qtpy
Requires-Dist: scikit-image
Requires-Dist: tifffile
Requires-Dist: tensorstore==0.1.59
Requires-Dist: ome-zarr==0.9.0
Requires-Dist: zarr<3.0.0,>=2.12.0
Requires-Dist: zarrdataset>=0.2.1
Provides-Extra: cellpose
Requires-Dist: cellpose>=3.0.0; extra == "cellpose"
Provides-Extra: testing
Requires-Dist: tox; extra == "testing"
Requires-Dist: pytest; extra == "testing"
Requires-Dist: pytest-cov; extra == "testing"
Requires-Dist: pytest-qt; extra == "testing"
Requires-Dist: napari; extra == "testing"
Requires-Dist: pyqt5; extra == "testing"
Dynamic: license-file
